flaskwebgui.py
flaskwebgui-1.1.6.dist-info/LICENSE
flaskwebgui-1.1.6.dist-info/METADATA
flaskwebgui-1.1.6.dist-info/WHEEL
flaskwebgui-1.1.6.dist-info/top_level.txt
flaskwebgui-1.1.6.dist-info/RECORD
