Metadata-Version: 2.1
Name: flaskwebgui
Version: 1.1.6
Summary: Create desktop applications with Flask/Django/FastAPI!
Home-page: https://github.com/ClimenteA/flaskwebgui
Author: Climente Alin
Author-email: climente.alin@gmail.com
License: MIT
License-File: LICENSE
Requires-Dist: psutil~=6.0
